aquiladb/AquilaDB.py
aquiladb/__init__.py
aquiladb/vecdb_pb2.py
aquiladb/vecdb_pb2_grpc.py
aquiladb-0.5.1.dist-info/LICENSE
aquiladb-0.5.1.dist-info/METADATA
aquiladb-0.5.1.dist-info/WHEEL
aquiladb-0.5.1.dist-info/top_level.txt
aquiladb-0.5.1.dist-info/RECORD
