Metadata-Version: 2.1
Name: aquiladb
Version: 0.5.1
Summary: Python client library for AquilaDB
Home-page: https://github.com/a-mma/AquilaDB-Python
Author: Harold Gomez
Author-email: haroldgmz11@gmail.com
License: UNKNOWN
Platform: UNKNOWN
Classifier: Programming Language :: Python :: 3
Classifier: License :: OSI Approved :: MIT License
Classifier: Operating System :: OS Independent
Requires-Dist: grpcio
Requires-Dist: protobuf
